{
  "id": 43,
  "name": "Shmi Skywalker",
  "height": 1.63,
  "gender": "female",
  "homeworld": "tatooine",
  "wiki": "http://starwars.wikia.com/wiki/Shmi_Skywalker_Lars",
  "image": "https://vignette.wikia.nocookie.net/starwars/images/a/ad/ShmiSkywalkerDatabank_%28Repurposed%29.jpeg",
  "born": -72,
  "died": -22,
  "diedLocation": "tatooine",
  "species": "human",
  "hairColor": "brown",
  "eyeColor": "brown",
  "skinColor": "light",
  "affiliations": [
    "Skywalker family",
    "Lars family"
  ],
  "formerAffiliations": []
}